optres/__init__.py
optres/option.py
optres/result.py
optres-0.1.0.dist-info/METADATA
optres-0.1.0.dist-info/LICENSE
optres-0.1.0.dist-info/WHEEL
optres-0.1.0.dist-info/RECORD
