Metadata-Version: 2.1
Name: optres
Version: 0.1.0
Summary: Yet another Rust's Option<T> and Result<T, E> simple implementation in Python.
Home-page: https://github.com/kagemeka/optres#readme
License: Apache-2.0
Keywords: rust,option,result
Author: kagemeka
Author-email: kagemeka1@gmail.com
Requires-Python: >=3.10,<4.0
Classifier: License :: OSI Approved :: Apache Software License
Classifier: Programming Language :: Python :: 3
Classifier: Programming Language :: Python :: 3.10
Classifier: Programming Language :: Python :: 3.11
Project-URL: Documentation, https://kagemeka.github.io/optres
Project-URL: Repository, https://github.com/kagemeka/optres
